{"rysiek": ["Bram_Finkel", "petercoffin"], "carlchenet": ["PocketRep", "jenesuispasgoth", "Lopinel", "pirboazo", "paulfree14", "muarf", "Milady", "yannjeg", "katyucha", "petercoffin", "kylinx", "patchidem"], "paulfree14": ["carlchenet", "muarf", "dracaenias", "mistur", "Gritche", "alexandrearchambault", "Giribot", "adericbourg", "arthak", "GeoffreyDorne", "Zestryon", "ymmg", "jenesuispasgoth", "unickuity", "reflets", "katyucha", "petercoffin", "LoboTom", "ThTh", "TouitTouit", "Dju", "THD_IT", "legrugru", "HyP"], "muarf": ["PocketRep", "paulfree14", "carlchenet", "alexandrearchambault", "reflets", "TouitTouit", "legrugru"], "dracaenias": ["paulfree14", "petercoffin"], "aoxyl": [], "mistur": ["ThTh", "paulfree14", "Dju", "alexandrearchambault", "reflets", "THD_IT", "legrugru"], "Gritche": ["paulfree14"], "Nico3333fr": [], "alexandrearchambault": ["Lopinel", "TouitTouit", "pirboazo", "legrugru", "averell", "paulfree14", "muarf", "mistur", "yannjeg", "Zestryon", "Giribot", "adericbourg", "kylinx", "patchidem", "reflets"], "Giribot": ["legrugru", "Lopinel", "pirboazo", "alexandrearchambault", "BrunoBellamy", "adericbourg", "paulfree14", "patchidem", "reflets"], "adericbourg": ["Giribot", "paulfree14", "alexandrearchambault"], "carballada": ["legrugru"], "kylinx": ["carlchenet", "alexandrearchambault", "GeoffreyDorne", "Zestryon", "reflets", "TouitTouit", "THD_IT", "legrugru"], "Korz": [], "arthak": ["pcouzon", "paulfree14"], "pirboazo": ["carlchenet", "alexandrearchambault", "Giribot", "GeoffreyDorne", "Zestryon", "jenesuispasgoth"], "GeoffreyDorne": ["Lopinel", "pirboazo", "Zestryon", "Bram_Finkel", "pcouzon", "paulfree14", "kylinx", "patchidem", "reflets"], "pcouzon": ["arthak", "GeoffreyDorne", "Zestryon", "reflets", "LoboTom"], "Milady": ["katyucha", "patchidem", "carlchenet"], "Zestryon": ["TouitTouit", "Lopinel", "pirboazo", "THD_IT", "BrunoBellamy", "pcouzon", "paulfree14", "HyP", "alexandrearchambault", "kylinx", "patchidem", "GeoffreyDorne", "legrugru"], "ymmg": ["paulfree14"], "Bram_Finkel": ["ThTh", "yourmarklubbers", "rysiek", "HyP", "GeoffreyDorne", "PocketRep", "jenesuispasgoth", "reflets", "petercoffin", "LoboTom"], "patchidem": ["carlchenet", "alexandrearchambault", "Giribot", "GeoffreyDorne", "Milady", "Zestryon", "jenesuispasgoth", "reflets", "LoboTom", "ThTh", "TouitTouit", "THD_IT", "legrugru"], "PocketRep": ["Bram_Finkel", "carlchenet", "muarf", "petercoffin"], "gilbertglee": [], "jenesuispasgoth": ["Lopinel", "pirboazo", "Bram_Finkel", "paulfree14", "patchidem", "carlchenet", "legrugru"], "Lopinel": ["carlchenet", "alexandrearchambault", "Giribot", "GeoffreyDorne", "Zestryon", "jenesuispasgoth", "reflets", "LoboTom", "ThTh", "TouitTouit", "THD_IT", "legrugru", "HyP"], "yourmarklubbers": ["Bram_Finkel", "petercoffin", "ThTh", "HyP"], "unickuity": ["paulfree14"], "BrunoBellamy": ["Giribot", "Zestryon"], "averell": ["alexandrearchambault", "ThTh", "THD_IT", "legrugru"], "reflets": ["Lopinel", "paulfree14", "muarf", "mistur", "katyucha", "alexandrearchambault", "Giribot", "petercoffin", "LoboTom", "kylinx", "ThTh", "myckeul", "TouitTouit", "GeoffreyDorne", "pcouzon", "HyP", "yannjeg", "Bram_Finkel", "patchidem"], "katyucha": ["carlchenet", "paulfree14", "Milady", "reflets", "legrugru"], "petercoffin": ["PocketRep", "rysiek", "yourmarklubbers", "Bram_Finkel", "paulfree14", "carlchenet", "dracaenias", "reflets", "ThTh"], "LoboTom": ["Lopinel", "Bram_Finkel", "pcouzon", "paulfree14", "patchidem", "reflets", "legrugru"], "Harmonia_Amanda": ["THD_IT"], "ThTh": ["mistur", "Lopinel", "yourmarklubbers", "averell", "paulfree14", "petercoffin", "patchidem", "Bram_Finkel", "reflets", "legrugru"], "dmcblue": [], "myckeul": ["reflets"], "TouitTouit": ["Lopinel", "THD_IT", "paulfree14", "muarf", "reflets", "Zestryon", "alexandrearchambault", "kylinx", "patchidem", "legrugru"], "Dju": ["mistur", "paulfree14"], "THD_IT": ["Lopinel", "TouitTouit", "averell", "paulfree14", "Harmonia_Amanda", "mistur", "yannjeg", "Zestryon", "kylinx", "patchidem"], "legrugru": ["ThTh", "jenesuispasgoth", "TouitTouit", "Lopinel", "averell", "paulfree14", "muarf", "HyP", "mistur", "kylinx", "yannjeg", "katyucha", "alexandrearchambault", "Zestryon", "Giribot", "carballada", "LoboTom", "patchidem"], "vimes79": [], "yapret": [], "maxencee": [], "HyP": ["Bram_Finkel", "paulfree14", "yourmarklubbers", "Lopinel", "Zestryon", "reflets", "legrugru"], "GingerForce": [], "Purply": [], "yannjeg": ["carlchenet", "alexandrearchambault", "reflets", "THD_IT", "legrugru"], "U039b": []}